README.rst
setup.py
flexpepdock/__init__.py
flexpepdock/batchUpload.py
flexpepdock.egg-info/PKG-INFO
flexpepdock.egg-info/SOURCES.txt
flexpepdock.egg-info/dependency_links.txt
flexpepdock.egg-info/entry_points.txt
flexpepdock.egg-info/requires.txt
flexpepdock.egg-info/top_level.txt
flexpepdock.egg-info/zip-safe